meta/__init__.py
meta/config.py
meta/log.py
meta/cli/__init__.py
meta/cli/auth.py
meta/marray/__init__.py
meta/marray/array.py
meta/marray/config.py
meta/utils/__init__.py
meta/utils/store_control.py
meta/utils/verify.py
meta_array_beta-0.2.5.dist-info/METADATA
meta_array_beta-0.2.5.dist-info/RECORD
meta_array_beta-0.2.5.dist-info/WHEEL
meta_array_beta-0.2.5.dist-info/entry_points.txt
meta_array_beta-0.2.5.dist-info/top_level.txt
